aiger_bv/__init__.py
aiger_bv/aigbv.py
aiger_bv/bundle.py
aiger_bv/common.py
aiger_bv/expr.py
py_aiger_bv-4.7.8.dist-info/LICENSE
py_aiger_bv-4.7.8.dist-info/METADATA
py_aiger_bv-4.7.8.dist-info/WHEEL
py_aiger_bv-4.7.8.dist-info/RECORD
