Metadata-Version: 2.1
Name: py-aiger-bv
Version: 4.7.8
Summary: A python library for manipulating sequential and-inverter gates.
License: MIT
Author: Marcell Vazquez-Chanlatte
Author-email: mvc@linux.com
Requires-Python: >=3.7,<4.0
Classifier: License :: OSI Approved :: MIT License
Classifier: Programming Language :: Python :: 3
Classifier: Programming Language :: Python :: 3.7
Classifier: Programming Language :: Python :: 3.8
Classifier: Programming Language :: Python :: 3.9
Classifier: Programming Language :: Python :: 3.10
Classifier: Programming Language :: Python :: 3.11
Classifier: Programming Language :: Python :: 3.12
Requires-Dist: attrs (>=22)
Requires-Dist: funcy (>=1.12,<2.0)
Requires-Dist: py-aiger (>=7,<8)
Requires-Dist: pyrsistent (>=0.19,<0.20)
